{"heroRelationship":[{"relationshipName":"最佳搭档","ids":"150|154"},{"relationshipName":"压制英雄","ids":"152|133"},{"relationshipName":"被压制英雄","ids":"156|141"}],"skillUpSuggest":{"summonerIds":"80115|80108","skillUpIds":"18010.png|18020.png"},"sound":"180.mp3","cname":"哪吒","heroId":180,"description":"\u201c我，哪吒，是人，又非人。\u201d \u201c炼金术炼成的身体，没有触觉，没有痛感，永远都无法长大。可胸腔里跳动着，乃真真正正，生而为人的心脏。\u201d \u201c东海边曾矗立着名叫陈塘关的城市，父亲乃此地长官。从小，我就清楚自己的强大，力量，速度与武技的领悟都凌驾常人。连兄长们也望尘莫及。\u201d \u201c可我没有朋友。无法抑制暴走的冲动，让同龄人都对我敬而远之。\u201d \u201c当权者下令父亲送我入起源之地作为人质。随行的只有太二。那里辉煌又无聊，忍不住搞点大事来。越自命不凡的家伙越叫人乐于招惹，最喜欢他们恨得牙痒痒又无可奈何的样子。这时候，他们面对魔种啊，平民啊的趾高气昂半点不剩了！我疯起来连我自己都害怕，何况这群懦夫。\u201d \u201c格格不入的不止我一人。我与那傲慢的杨戬之间本唯有拳头的交往，可有天从纨绔们的手中救了只丑得要命的流浪狗，还毫不领情冲我狂吠时，杨戬一把将它拎了回去。呃，这画风有什么地方不对呀。\u201d \u201c那天起\u2026\u2026似乎多了种心照不宣的默契。好像\u2026\u2026朋友通常如此？\u201d \u201c报复心切的纨绔们举报太二为逃犯，害他蹲进大牢。正好我厌烦了这令人窒息的牢笼，一不做二不休来了场酣畅淋漓的逃狱。有人追了上来。忘恩负义的流浪狗不停狂吠，在我几乎要出手凑它前的0.1秒，杨戬让开了道路。\u201d \u201c陈塘关已和平不再。当权者要父亲剿灭海中的大型魔种。显然，这是对我出逃的惩罚。\u201d \u201c魔种发了狂。父亲说。它们会越来越危险。\u201d \u201c安享和平多年渔民，商人和妇孺怎么可能是魔种的对手？\u201d \u201c还有陷阱。最后他喃喃道。\u201d \u201c愤怒爆发了！愤怒支配了我！我疯狂的想要破坏引水的沟渠，还有作为陷阱的城墙。就在那晚，暴风雨比预计的更加提前到来。我眼看着渔船被狂怒的魔种吞噬时，身后的故乡也变成了汪洋。陈塘关以淹没自身为代价，囚困了比自己强大百倍的狩猎对象。胸腔中燃烧的愤怒席卷了海潮，吞噬掉了魔种，也吞噬了我自己。\u201d \u201c从炼成阵里，我重新获得了生命。\u201d \u201c可有什么跟之前不一样了。\u201d \u201c心脏。我摸着胸口。持续跳动的，强有力的心脏。\u201d \u201c最后关头，天下第一的傻瓜师父，太二，献祭了自己来拯救我。\u201d \u201c我突然间品尝到愤怒之外的其他情绪，过往生命中从未存在的感受：亲切，犹豫，愧疚，思念，哀悼，友情\u2026\u2026以及\u2026\u2026嫌弃\u2026\u2026唉，这过时的发型，充分说明了太二品味有多么捉急。\u201d \u201c我还是桀骜的我，但背负了更多的什么\u2026\u2026\u201d \u201c太二奇迹般的生存。他的道歉模糊而混乱：钥匙\u2026\u2026奇迹\u2026\u2026难懂的词汇\u2026\u2026我不想知道所有的由来。我不过想保护陈塘关，我不过想保护我所生活的故乡。\u201d \u201c谁造成这一切？魔种的罪孽，抑或当权者的冷酷？\u201d \u201c谁在乎。\u201d \u201c没有牵挂，只会让我更强大。我要选择自己的路，去守护我想守护的，改变我想改变的了！\u201d \u201c我可是突破常理的存在！\u201d","mingwenSuggestInfo":"1504|3516|2501","suggestEquipments":[{"periodName":"前期装备","ids":"1311"},{"periodName":"中期装备","ids":"1331|1422|1137"},{"periodName":"后期装备","ids":"1331|1422|1137|1335|1333|1337"}],"title":"桀骜炎枪","skills":[{"skillName":"炙炼火种","coolingValue":"冷却值：0","skillImg":"1800.png","costValue":"消耗：0","skillDesc":"被动：哪吒每次用枪造成的伤害和使用乾坤圈都会在敌人身上残留炙炼火种造成灼烧伤害并且限制目标的生命回复"},{"skillName":"火焰三尖枪","coolingValue":"冷却值：5","skillImg":"1810.png","costValue":"消耗：55","skillDesc":"哪吒挥枪攻击四周的敌人造成物理伤害。每击中一个敌方英雄都会获得风火轮提供移动加速效果，加速持续一段时间"},{"skillName":"混天绫·束","coolingValue":"冷却值：12","skillImg":"1820.png","costValue":"消耗：65","skillDesc":"哪吒用混天绫短暂束缚敌人，迅速俯冲向目标，并翻越至目标另一侧。施法后自动触发【火莲之印】减免所受伤害。【火莲之印】持续短暂时间，该技能短时间内可再次释放"},{"skillName":"乾坤·天降","coolingValue":"冷却值：80","skillImg":"1830.png","costValue":"消耗：140","skillDesc":"对敌英雄施加乾坤圈提供视野并打断其回城。可选择高速冲到敌方英雄造成物理伤害并击退，落地后触发一次【火莲之印】，并额外触发【火莲之华】获得韧性且每秒对罩内敌人反复施加炙炼火种"}],"hero_type":1,"attribute":[{"name":"生存能力","value":"80"},{"name":"攻击伤害","value":"60"},{"name":"技能效果","value":"60"},{"name":"上手难度","value":"80"}],"skin_names":"桀骜炎枪|三太子"}